deltabot_cli/__init__.py
deltabot_cli/_utils.py
deltabot_cli/cli.py
deltabot_cli-8.0.0.dist-info/licenses/LICENSE
deltabot_cli-8.0.0.dist-info/METADATA
deltabot_cli-8.0.0.dist-info/WHEEL
deltabot_cli-8.0.0.dist-info/top_level.txt
deltabot_cli-8.0.0.dist-info/RECORD
