Metadata-Version: 2.4
Name: deltabot-cli
Version: 8.0.0
Summary: Library to speedup Delta Chat bot development
Author-email: adbenitez <adb@merlinux.eu>
Project-URL: Homepage, https://github.com/deltachat-bot/deltabot-cli-py
Keywords: deltachat,bot,deltabot-cli
Classifier: Development Status :: 4 - Beta
Classifier: Programming Language :: Python :: 3
Classifier: Intended Audience :: Developers
Classifier: License :: OSI Approved :: Mozilla Public License 2.0 (MPL 2.0)
Requires-Python: >=3.8
License-File: LICENSE
Requires-Dist: deltachat2[full]>=0.8.0
Requires-Dist: appdirs>=1.4.4
Requires-Dist: rich>=12.6.0
Provides-Extra: dev
Requires-Dist: black; extra == "dev"
Requires-Dist: mypy; extra == "dev"
Requires-Dist: isort; extra == "dev"
Requires-Dist: pylint; extra == "dev"
Requires-Dist: pylama; extra == "dev"
Requires-Dist: pytest; extra == "dev"
Dynamic: license-file
